[
    {
        "slug": "introducao-pentest",
        "title": "Introdução ao Pentest: Primeiros Passos",
        "date": "2026-06-21",
        "tags": ["Pentest", "Iniciante"],
        "excerpt": "Aprenda os conceitos fundamentais do teste de invasão..."
    },
    {
        "slug": "ferramentas-nmap",
        "title": "Nmap: A Ferramenta Essencial para Reconhecimento",
        "date": "2026-06-19",
        "tags": ["Ferramentas", "Reconhecimento"],
        "excerpt": "Domine o Nmap e aprenda a mapear redes..."
    }
]
